pixelcolor/__init__.py
pixelcolor/command_line_options.py
pixelcolor/constants.py
pixelcolor/main.py
pixelcolor/pixel_color.py
PixelColor-0.2.0.dist-info/LICENSE
PixelColor-0.2.0.dist-info/METADATA
PixelColor-0.2.0.dist-info/WHEEL
PixelColor-0.2.0.dist-info/entry_points.txt
PixelColor-0.2.0.dist-info/top_level.txt
PixelColor-0.2.0.dist-info/RECORD
