Metadata-Version: 2.1
Name: PixelColor
Version: 0.2.0
Summary: Get the screen pixel color
Home-page: http://www.muflone.com/pixelcolor/
Author: Fabio Castelli
Author-email: muflone@muflone.com
License: GPLv3+
Classifier: Development Status :: 1 - Planning
Classifier: Intended Audience :: Developers
Classifier: License :: OSI Approved :: GNU General Public License v3 or later (GPLv3+)
Classifier: Operating System :: OS Independent
Classifier: Programming Language :: Python :: 3
Classifier: Programming Language :: Python :: 3.9
Classifier: Programming Language :: Python :: 3.10
Classifier: Topic :: Software Development :: Libraries :: Python Modules
License-File: LICENSE
Requires-Dist: pillow (==9.3.0)
